seraschars/__init__.py
seraschars/character.py
seraschars-0.1.2.dist-info/METADATA
seraschars-0.1.2.dist-info/WHEEL
seraschars-0.1.2.dist-info/top_level.txt
seraschars-0.1.2.dist-info/RECORD
