Metadata-Version: 2.4
Name: seraschars
Version: 0.1.2
Summary: a small module for setting up personas
Author: sz
License: MIT
Requires-Python: >=3.9
